{
  "_type": "export",
  "__export_format": 4,
  "__export_date": "2025-10-10T00:00:00.000Z",
  "__export_source": "insomnia.desktop.app:v8.6.1",
  "resources": [
    {
      "_id": "req_profile_create",
      "parentId": "fld_profile",
      "modified": 1728518400000,
      "created": 1728518400000,
      "url": "{{ _.base_url }}/profile",
      "name": "Create Profile",
      "description": "Criar um novo perfil (apenas ADMIN)",
      "method": "POST",
      "body": {
        "mimeType": "application/json",
        "text": "{\n  \"name\": \"João Silva\",\n  \"email\": \"joao.silva@email.com\",\n  \"password\": \"senha123\",\n  \"phone\": \"11999888777\",\n  \"role\": 0,\n  \"birth\": \"1990-05-15\",\n  \"height\": 175,\n  \"weight\": 80,\n  \"trainerId\": null\n}"
      },
      "parameters": [],
      "headers": [
        {
          "id": "pair_content_type",
          "name": "Content-Type",
          "value": "application/json",
          "description": ""
        },
        {
          "id": "pair_authorization",
          "name": "Authorization",
          "value": "Bearer {{ _.access_token }}",
          "description": ""
        }
      ],
      "authentication": {},
      "metaSortKey": -1728518400000,
      "isPrivate": false,
      "settingStoreCookies": true,
      "settingSendCookies": true,
      "settingDisableRenderRequestBody": false,
      "settingEncodeUrl": true,
      "settingRebuildPath": true,
      "settingFollowRedirects": "global",
      "_type": "request"
    },
    {
      "_id": "req_profile_create_trainer",
      "parentId": "fld_profile",
      "modified": 1728518400000,
      "created": 1728518400000,
      "url": "{{ _.base_url }}/profile",
      "name": "Create Trainer Profile",
      "description": "Criar um perfil de treinador (apenas ADMIN)",
      "method": "POST",
      "body": {
        "mimeType": "application/json",
        "text": "{\n  \"name\": \"Maria Personal\",\n  \"email\": \"maria.personal@email.com\",\n  \"password\": \"senha123\",\n  \"phone\": \"11888777666\",\n  \"role\": 1,\n  \"birth\": \"1985-03-20\",\n  \"height\": 165,\n  \"weight\": 60,\n  \"trainerId\": null\n}"
      },
      "parameters": [],
      "headers": [
        {
          "id": "pair_content_type",
          "name": "Content-Type",
          "value": "application/json",
          "description": ""
        },
        {
          "id": "pair_authorization",
          "name": "Authorization",
          "value": "Bearer {{ _.access_token }}",
          "description": ""
        }
      ],
      "authentication": {},
      "metaSortKey": -1728518390000,
      "isPrivate": false,
      "settingStoreCookies": true,
      "settingSendCookies": true,
      "settingDisableRenderRequestBody": false,
      "settingEncodeUrl": true,
      "settingRebuildPath": true,
      "settingFollowRedirects": "global",
      "_type": "request"
    },
    {
      "_id": "req_profile_findall",
      "parentId": "fld_profile",
      "modified": 1728518400000,
      "created": 1728518400000,
      "url": "{{ _.base_url }}/profile",
      "name": "Get All Profiles",
      "description": "Buscar todos os perfis (baseado no role do usuário)",
      "method": "GET",
      "body": {},
      "parameters": [],
      "headers": [
        {
          "id": "pair_authorization",
          "name": "Authorization",
          "value": "Bearer {{ _.access_token }}",
          "description": ""
        }
      ],
      "authentication": {},
      "metaSortKey": -1728518300000,
      "isPrivate": false,
      "settingStoreCookies": true,
      "settingSendCookies": true,
      "settingDisableRenderRequestBody": false,
      "settingEncodeUrl": true,
      "settingRebuildPath": true,
      "settingFollowRedirects": "global",
      "_type": "request"
    },
    {
      "_id": "req_profile_findone",
      "parentId": "fld_profile",
      "modified": 1728518400000,
      "created": 1728518400000,
      "url": "{{ _.base_url }}/profile/{{ _.profile_id }}",
      "name": "Get Profile by ID",
      "description": "Buscar um perfil específico por ID",
      "method": "GET",
      "body": {},
      "parameters": [],
      "headers": [
        {
          "id": "pair_authorization",
          "name": "Authorization",
          "value": "Bearer {{ _.access_token }}",
          "description": ""
        }
      ],
      "authentication": {},
      "metaSortKey": -1728518200000,
      "isPrivate": false,
      "settingStoreCookies": true,
      "settingSendCookies": true,
      "settingDisableRenderRequestBody": false,
      "settingEncodeUrl": true,
      "settingRebuildPath": true,
      "settingFollowRedirects": "global",
      "_type": "request"
    },
    {
      "_id": "req_profile_update",
      "parentId": "fld_profile",
      "modified": 1728518400000,
      "created": 1728518400000,
      "url": "{{ _.base_url }}/profile/{{ _.profile_id }}",
      "name": "Update Profile",
      "description": "Atualizar um perfil específico",
      "method": "PATCH",
      "body": {
        "mimeType": "application/json",
        "text": "{\n  \"name\": \"João Silva Santos\",\n  \"phone\": \"11999888777\",\n  \"height\": 176,\n  \"weight\": 82\n}"
      },
      "parameters": [],
      "headers": [
        {
          "id": "pair_content_type",
          "name": "Content-Type",
          "value": "application/json",
          "description": ""
        },
        {
          "id": "pair_authorization",
          "name": "Authorization",
          "value": "Bearer {{ _.access_token }}",
          "description": ""
        }
      ],
      "authentication": {},
      "metaSortKey": -1728518100000,
      "isPrivate": false,
      "settingStoreCookies": true,
      "settingSendCookies": true,
      "settingDisableRenderRequestBody": false,
      "settingEncodeUrl": true,
      "settingRebuildPath": true,
      "settingFollowRedirects": "global",
      "_type": "request"
    },
    {
      "_id": "req_profile_assign_trainer",
      "parentId": "fld_profile",
      "modified": 1728518400000,
      "created": 1728518400000,
      "url": "{{ _.base_url }}/profile/{{ _.profile_id }}",
      "name": "Assign Trainer to Profile",
      "description": "Atribuir um treinador a um aluno",
      "method": "PATCH",
      "body": {
        "mimeType": "application/json",
        "text": "{\n  \"trainerId\": \"{{ _.trainer_id }}\"\n}"
      },
      "parameters": [],
      "headers": [
        {
          "id": "pair_content_type",
          "name": "Content-Type",
          "value": "application/json",
          "description": ""
        },
        {
          "id": "pair_authorization",
          "name": "Authorization",
          "value": "Bearer {{ _.access_token }}",
          "description": ""
        }
      ],
      "authentication": {},
      "metaSortKey": -1728518090000,
      "isPrivate": false,
      "settingStoreCookies": true,
      "settingSendCookies": true,
      "settingDisableRenderRequestBody": false,
      "settingEncodeUrl": true,
      "settingRebuildPath": true,
      "settingFollowRedirects": "global",
      "_type": "request"
    },
    {
      "_id": "req_profile_delete",
      "parentId": "fld_profile",
      "modified": 1728518400000,
      "created": 1728518400000,
      "url": "{{ _.base_url }}/profile/{{ _.profile_id }}",
      "name": "Delete Profile",
      "description": "Deletar um perfil específico (apenas ADMIN)",
      "method": "DELETE",
      "body": {},
      "parameters": [],
      "headers": [
        {
          "id": "pair_authorization",
          "name": "Authorization",
          "value": "Bearer {{ _.access_token }}",
          "description": ""
        }
      ],
      "authentication": {},
      "metaSortKey": -1728518000000,
      "isPrivate": false,
      "settingStoreCookies": true,
      "settingSendCookies": true,
      "settingDisableRenderRequestBody": false,
      "settingEncodeUrl": true,
      "settingRebuildPath": true,
      "settingFollowRedirects": "global",
      "_type": "request"
    },
    {
      "_id": "fld_profile",
      "parentId": "wrk_main",
      "modified": 1728518400000,
      "created": 1728518400000,
      "name": "Profile Module",
      "description": "Endpoints para gerenciamento de perfis de usuários",
      "environment": {},
      "environmentPropertyOrder": null,
      "metaSortKey": -1728518400000,
      "_type": "request_group"
    },
    {
      "_id": "wrk_main",
      "parentId": null,
      "modified": 1728518400000,
      "created": 1728518400000,
      "name": "Gym Management API",
      "description": "API para gerenciamento de academia",
      "scope": "collection",
      "_type": "workspace"
    },
    {
      "_id": "env_base",
      "parentId": "wrk_main",
      "modified": 1728518400000,
      "created": 1728518400000,
      "name": "Base Environment",
      "data": {
        "base_url": "http://localhost:3333",
        "access_token": "",
        "refresh_token": "",
        "profile_id": "",
        "trainer_id": ""
      },
      "dataPropertyOrder": {
        "&": [
          "base_url",
          "access_token", 
          "refresh_token",
          "profile_id",
          "trainer_id"
        ]
      },
      "color": null,
      "isPrivate": false,
      "metaSortKey": 1728518400000,
      "_type": "environment"
    }
  ]
}